pyfuse/__init__.py
pyfuse/py.typed
pyfuse/cli/__init__.py
pyfuse/cli/builders.py
pyfuse/cli/config.py
pyfuse/cli/dashboard.py
pyfuse/cli/learn.py
pyfuse/cli/main.py
pyfuse/cli/vm.py
pyfuse/cli/lint/__init__.py
pyfuse/cli/lint/flake8_empty_element.py
pyfuse/core/__init__.py
pyfuse/core/_greenlet_guard.py
pyfuse/core/component.py
pyfuse/core/computed.py
pyfuse/core/context.py
pyfuse/core/effect.py
pyfuse/core/element.py
pyfuse/core/injection.py
pyfuse/core/protocol.py
pyfuse/core/registry.py
pyfuse/core/router.py
pyfuse/core/scheduler.py
pyfuse/core/signal.py
pyfuse/core/style/__init__.py
pyfuse/core/style/colors.py
pyfuse/core/style/style.py
pyfuse/core/utils/__init__.py
pyfuse/core/utils/loader.py
pyfuse/tui/__init__.py
pyfuse/tui/adapter.py
pyfuse/tui/builder.py
pyfuse/tui/runtime.py
pyfuse/tui/layout/CLAUDE.md
pyfuse/tui/layout/__init__.py
pyfuse/tui/layout/algorithm.py
pyfuse/tui/layout/baseline.py
pyfuse/tui/layout/cache.py
pyfuse/tui/layout/compute.py
pyfuse/tui/layout/direction.py
pyfuse/tui/layout/flexline.py
pyfuse/tui/layout/intrinsic.py
pyfuse/tui/layout/measure.py
pyfuse/tui/layout/node.py
pyfuse/tui/layout/parallel.py
pyfuse/tui/layout/reactive.py
pyfuse/tui/layout/style.py
pyfuse/tui/layout/style_resolver.py
pyfuse/tui/layout/types.py
pyfuse/tui/renderer/__init__.py
pyfuse/tui/renderer/ansi.py
pyfuse/tui/renderer/buffer.py
pyfuse/tui/renderer/cell.py
pyfuse/tui/renderer/diff.py
pyfuse/tui/renderer/input.py
pyfuse/tui/renderer/manifest.py
pyfuse/tui/renderer/output.py
pyfuse/tui/renderer/renderer.py
pyfuse/tui/renderer/runtime.py
pyfuse/tui/renderer/terminal.py
pyfuse/tui/renderer/theme.py
pyfuse/tui/testing/__init__.py
pyfuse/tui/testing/driver.py
pyfuse/tui/testing/locator.py
pyfuse/tui/testing/snapshot.py
pyfuse/tui/testing/stabilize.py
pyfuse/ui/__init__.py
pyfuse/ui/elements.py
pyfuse/ui/for_each.py
pyfuse/ui/layout.py
pyfuse/ui/spinner.py
pyfuse/web/__init__.py
pyfuse/web/build/__init__.py
pyfuse/web/build/artifacts.py
wtfui-0.1.0a1.dist-info/METADATA
wtfui-0.1.0a1.dist-info/WHEEL
wtfui-0.1.0a1.dist-info/entry_points.txt
wtfui-0.1.0a1.dist-info/licenses/LICENSE
wtfui-0.1.0a1.dist-info/RECORD
